main.py
setup.py
shadokv.egg-info/PKG-INFO
shadokv.egg-info/SOURCES.txt
shadokv.egg-info/dependency_links.txt
shadokv.egg-info/requires.txt
shadokv.egg-info/top_level.txt